pymodaq_plugins_keithley/__init__.py
pymodaq_plugins_keithley/utils.py
pymodaq_plugins_keithley/daq_move_plugins/__init__.py
pymodaq_plugins_keithley/daq_move_plugins/daq_move_Keithley2400.py
pymodaq_plugins_keithley/daq_viewer_plugins/__init__.py
pymodaq_plugins_keithley/daq_viewer_plugins/plugins_0D/__init__.py
pymodaq_plugins_keithley/daq_viewer_plugins/plugins_0D/daq_0Dviewer_Keithley2100.py
pymodaq_plugins_keithley/daq_viewer_plugins/plugins_0D/daq_0Dviewer_Keithley2110.py
pymodaq_plugins_keithley/daq_viewer_plugins/plugins_0D/daq_0Dviewer_Keithley27XX.py
pymodaq_plugins_keithley/daq_viewer_plugins/plugins_0D/daq_0Dviewer_Keithley_Pico.py
pymodaq_plugins_keithley/daq_viewer_plugins/plugins_1D/__init__.py
pymodaq_plugins_keithley/daq_viewer_plugins/plugins_2D/__init__.py
pymodaq_plugins_keithley/hardware/__init__.py
pymodaq_plugins_keithley/hardware/keithley2100/__init__.py
pymodaq_plugins_keithley/hardware/keithley2100/keithley2100_VISADriver.py
pymodaq_plugins_keithley/hardware/keithley2110/__init__.py
pymodaq_plugins_keithley/hardware/keithley2110/keithley2110_VISADriver.py
pymodaq_plugins_keithley/hardware/keithley27XX/__init__.py
pymodaq_plugins_keithley/hardware/keithley27XX/keithley27XX_VISADriver.py
pymodaq_plugins_keithley/resources/VERSION
pymodaq_plugins_keithley/resources/__init__.py
pymodaq_plugins_keithley/resources/config_template.toml
pymodaq_plugins_keithley-1.2.0.dist-info/LICENSE
pymodaq_plugins_keithley-1.2.0.dist-info/METADATA
pymodaq_plugins_keithley-1.2.0.dist-info/WHEEL
pymodaq_plugins_keithley-1.2.0.dist-info/entry_points.txt
pymodaq_plugins_keithley-1.2.0.dist-info/top_level.txt
pymodaq_plugins_keithley-1.2.0.dist-info/RECORD
