Metadata-Version: 2.1
Name: pymodaq_plugins_keithley
Version: 1.2.0
Summary: Set of PyMoDAQ plugins for various physical measurements from keithley
Home-page: https://github.com/PyMoDAQ/pymodaq_plugins_keithley
Author: Sébastien Weber
Author-email: sebastien.weber@cemes.fr
License: MIT
Classifier: Programming Language :: Python :: 3
Classifier: Development Status :: 5 - Production/Stable
Classifier: Environment :: Other Environment
Classifier: Intended Audience :: Science/Research
Classifier: Topic :: Scientific/Engineering :: Human Machine Interfaces
Classifier: Topic :: Scientific/Engineering :: Visualization
Classifier: License :: OSI Approved :: MIT License
Classifier: Operating System :: OS Independent
Classifier: Topic :: Software Development :: Libraries :: Python Modules
Classifier: Topic :: Software Development :: User Interfaces
License-File: LICENSE
Requires-Dist: toml
Requires-Dist: pyvisa
Requires-Dist: pyvisa-py
Requires-Dist: pymeasure
Requires-Dist: pymodaq>=4.0
